aptools/__init__.py
aptools/helper_functions.py
aptools/data_analysis/__init__.py
aptools/data_analysis/beam_diagnostics.py
aptools/data_handling/__init__.py
aptools/data_handling/conversion.py
aptools/data_handling/reading.py
aptools/data_handling/saving.py
aptools/data_handling/utilities.py
aptools/data_processing/__init__.py
aptools/data_processing/beam_filtering.py
aptools/data_processing/beam_operations.py
aptools/particle_distributions/__init__.py
aptools/particle_distributions/particle_distribution.py
aptools/particle_distributions/read.py
aptools/particle_distributions/save.py
aptools/plasma_accel/__init__.py
aptools/plasma_accel/general_equations.py
aptools/plasma_accel/matching.py
aptools/plotting/__init__.py
aptools/plotting/plot_types.py
aptools/plotting/quick_diagnostics.py
aptools/plotting/rc_params.py
aptools/plotting/utils.py
aptools/utilities/__init__.py
aptools/utilities/bunch_generation.py
APtools-0.2.5.dist-info/LICENSE
APtools-0.2.5.dist-info/METADATA
APtools-0.2.5.dist-info/WHEEL
APtools-0.2.5.dist-info/top_level.txt
APtools-0.2.5.dist-info/RECORD
