Metadata-Version: 2.1
Name: APtools
Version: 0.2.5
Summary: A collection of tools for accelerator physics
Home-page: https://github.com/AngelFP/APtools
Author: Angel Ferran Pousa
Author-email: angel.ferran.pousa@desy.de,
License: GPLv3
Classifier: Development Status :: 3 - Alpha
Classifier: Programming Language :: Python :: 3
Classifier: Intended Audience :: Science/Research
Classifier: Topic :: Scientific/Engineering :: Physics
Classifier: License :: OSI Approved :: GNU General Public License v3 (GPLv3)
Classifier: Operating System :: OS Independent
License-File: LICENSE
Requires-Dist: numpy
Requires-Dist: scipy
Requires-Dist: h5py
Requires-Dist: openpmd-api
Requires-Dist: deprecated
